better_profanity/__init__.py
better_profanity/alphabetic_unicode.json
better_profanity/better_profanity.py
better_profanity/constants.py
better_profanity/profanity_wordlist.txt
better_profanity/utils.py
better_profanity-0.6.1.data/data/unicode_characters/alphabetic_unicode.json
better_profanity-0.6.1.data/data/wordlist/profanity_wordlist.txt
better_profanity-0.6.1.dist-info/LICENSE
better_profanity-0.6.1.dist-info/METADATA
better_profanity-0.6.1.dist-info/WHEEL
better_profanity-0.6.1.dist-info/top_level.txt
better_profanity-0.6.1.dist-info/RECORD
