Metadata-Version: 2.1
Name: better_profanity
Version: 0.6.1
Summary: Blazingly fast cleaning swear words (and their leetspeak) in strings
Home-page: https://github.com/snguyenthanh/better_profanity
Author: Son Nguyen Thanh
Author-email: thanhson16198@gmail.com
License: UNKNOWN
Platform: UNKNOWN
Classifier: Programming Language :: Python :: 3
Classifier: License :: OSI Approved :: MIT License
Classifier: Operating System :: OS Independent
Requires-Python: ==3.*
